openg2p_fastapi_auth_models/__init__.py
openg2p_fastapi_auth_models/context.py
openg2p_fastapi_auth_models/models/__init__.py
openg2p_fastapi_auth_models/models/login_provider.py
openg2p_fastapi_auth_models/schemas/__init__.py
openg2p_fastapi_auth_models/schemas/credentials.py
openg2p_fastapi_auth_models/schemas/login_provider.py
openg2p_fastapi_auth_models/schemas/provider_auth_parameters.py
openg2p_fastapi_auth_models-1.1.4.dist-info/METADATA
openg2p_fastapi_auth_models-1.1.4.dist-info/WHEEL
openg2p_fastapi_auth_models-1.1.4.dist-info/licenses/LICENSE
openg2p_fastapi_auth_models-1.1.4.dist-info/RECORD
